feazdata/__init__.py
feazdata/data/ames.csv
feazdata/data/animal-shelter-intakes-and-outcomes.csv
feazdata/data/flights.csv
feazdata/data/shelter_cats.R
feazdata/data/shelter_cats.csv
feazdata-0.0.3.dist-info/LICENSE
feazdata-0.0.3.dist-info/METADATA
feazdata-0.0.3.dist-info/WHEEL
feazdata-0.0.3.dist-info/top_level.txt
feazdata-0.0.3.dist-info/RECORD
